ejtraderDB/__init__.py
ejtraderDB/common.py
ejtraderDB/dict.py
ejtraderDB/exceptions.py
ejtraderDB/qdb_api.py
ejtraderDB/questdb.py
ejtraderDB/sqlackqueue.py
ejtraderDB/sqlbase.py
ejtraderDB/sqlqueue.py
ejtraderDB/serializers/__init__.py
ejtraderDB/serializers/json.py
ejtraderDB/serializers/msgpack.py
ejtraderDB/serializers/pickle.py
ejtraderDB-1.0.4.dist-info/LICENSE
ejtraderDB-1.0.4.dist-info/METADATA
ejtraderDB-1.0.4.dist-info/WHEEL
ejtraderDB-1.0.4.dist-info/top_level.txt
ejtraderDB-1.0.4.dist-info/RECORD
