Metadata-Version: 2.1
Name: ejtraderDB
Version: 1.0.4
Summary: SQlite and QuestDB
Home-page: https://ejtraderDB.readthedocs.io/
Download-URL: https://ejtrader.com
Author: Emerson Pedroso
Author-email: support@ejtrader.com
License: MIT License
Project-URL: Bug Reports, https://github.com/ejtraderLabs/ejtraderDB/issues
Project-URL: Source, https://github.com/ejtraderLabs/ejtraderDB
Project-URL: Documentation, https://ejtrader.readthedocs.io/
Keywords: metatrader,f-api,historical-data,financial-data,stocks,funds,etfs,indices,currency crosses,bonds,commodities,crypto currencies
Classifier: Programming Language :: Python :: 3 :: Only
Classifier: Programming Language :: Python :: 3.5
Classifier: Programming Language :: Python :: 3.6
Classifier: Programming Language :: Python :: 3.7
Classifier: Programming Language :: Python :: 3.8
Classifier: License :: OSI Approved :: MIT License
Classifier: Intended Audience :: Developers
Classifier: Topic :: Office/Business :: Financial
Classifier: Topic :: Office/Business :: Financial :: Investment
Classifier: Topic :: Scientific/Engineering :: Information Analysis
Classifier: Topic :: Software Development :: Libraries
Requires-Python: >=3
License-File: LICENSE
Requires-Dist: msgpack (>=0.5.6)
Requires-Dist: pandas (==1.3.4)
Requires-Dist: requests (==2.26.0)
Requires-Dist: sqlvalidator (==0.0.17)
